genieutils/__init__.py
genieutils/civ.py
genieutils/common.py
genieutils/datatypes.py
genieutils/datfile.py
genieutils/effect.py
genieutils/graphic.py
genieutils/playercolour.py
genieutils/randommaps.py
genieutils/scripts.py
genieutils/sound.py
genieutils/task.py
genieutils/tech.py
genieutils/techtree.py
genieutils/terrainblock.py
genieutils/terrainrestriction.py
genieutils/unit.py
genieutils/unitheaders.py
genieutils/versions.py
genieutils_py-0.1.1.dist-info/METADATA
genieutils_py-0.1.1.dist-info/WHEEL
genieutils_py-0.1.1.dist-info/entry_points.txt
genieutils_py-0.1.1.dist-info/licenses/LICENSE
genieutils_py-0.1.1.dist-info/RECORD
