Metadata-Version: 2.4
Name: genieutils-py
Version: 0.1.1
Summary: Re-implementation of genieutils in Python
Project-URL: Homepage, https://github.com/SiegeEngineers/genieutils-py
Project-URL: Issues, https://github.com/SiegeEngineers/genieutils-py/issues
Author-email: SiegeEngineers <genieutils@siegeengineers.org>
License-File: LICENSE
Classifier: License :: OSI Approved :: GNU Lesser General Public License v3 (LGPLv3)
Classifier: Operating System :: OS Independent
Classifier: Programming Language :: Python :: 3
Requires-Python: >=3.11
